pystockquery/__init__.py
pystockquery/api.py
pystockquery/data_handler.py
pystockquery/query_parser.py
pystockquery/visualization.py
pystockquery/data/merged_stock_data.xlsx
pystockquery-3.1.1.dist-info/METADATA
pystockquery-3.1.1.dist-info/WHEEL
pystockquery-3.1.1.dist-info/top_level.txt
pystockquery-3.1.1.dist-info/RECORD
