Metadata-Version: 2.4
Name: pystockquery
Version: 3.1.1
Summary: A natural language interface for stock data analysis
Home-page: https://github.com/yourusername/pystockquery
Author: Your Name
Author-email: your.email@example.com
Classifier: Programming Language :: Python :: 3
Classifier: License :: OSI Approved :: MIT License
Classifier: Operating System :: OS Independent
Requires-Python: >=3.6
Requires-Dist: pandas>=1.0.0
Requires-Dist: openpyxl>=3.0.0
Requires-Dist: matplotlib>=3.0.0
Requires-Dist: seaborn>=0.11.0
Dynamic: author
Dynamic: author-email
Dynamic: classifier
Dynamic: description
Dynamic: description-content-type
Dynamic: home-page
Dynamic: requires-dist
Dynamic: requires-python
Dynamic: summary
